[
  {
    "keyword": "AAA",
    "details_file": "output_wa4/bi_html/wa_bi_A_AAA.json",
    "details_success": 1,
    "details_failed": 24,
    "records_scraped": 25
  },
  {
    "keyword": "AAB",
    "details_file": "output_wa4/bi_html/wa_bi_A_AAB.json",
    "details_success": 1,
    "details_failed": 6,
    "records_scraped": 7
  },
  {
    "keyword": "AAC",
    "details_file": "output_wa4/bi_html/wa_bi_A_AAC.json",
    "details_success": 1,
    "details_failed": 9,
    "records_scraped": 10
  },
  {
    "keyword": "AAD",
    "details_file": "output_wa4/bi_html/wa_bi_A_AAD.json",
    "details_success": 1,
    "details_failed": 7,
    "records_scraped": 8
  }
]